AUTHORS
CHANGES
COPYING
README
RELEASE.howto
setup.py
boletin/__init__.py
boletin/admin.py
boletin/forms.py
boletin/models.py
boletin/tests.py
boletin/tests_urls.py
boletin/urls.py
boletin/views.py
boletin.egg-info/PKG-INFO
boletin.egg-info/SOURCES.txt
boletin.egg-info/dependency_links.txt
boletin.egg-info/not-zip-safe
boletin.egg-info/top_level.txt
boletin/cron/create-newsletter
boletin/cron/send-newsletter
boletin/management/__init__.py
boletin/management/commands/__init__.py
boletin/management/commands/createnewsletter.py
boletin/management/commands/sendnewsletter.py
boletin/management/commands/shownewsletters.py
boletin/templates/base.html
boletin/templates/boletin/newsletter.html
boletin/templates/boletin/newsletter_base.html
boletin/templates/boletin/newsletter_confirm.html
boletin/templates/boletin/newsletter_confirm_email.txt
boletin/templates/boletin/newsletter_email.html
boletin/templates/boletin/newsletter_email.txt
boletin/templates/boletin/newsletter_success.html
boletin/templates/boletin/newsletter_unsubscription_confirm.html
boletin/templates/boletin/newsletter_unsubscription_confirm_email.txt
boletin/templates/boletin/newsletter_unsubscription_success.html
boletin/templates/boletin/reviewer_email.txt
boletin/templatetags/__init__.py
boletin/templatetags/stringfilters.py