Metadata-Version: 1.0
Name: boletin
Version: 0.5.1
Summary: Newsletter generation and sending application for Django
Home-page: https://tracpub.yaco.es/djangoapps/wiki/Boletin
Author: Fidel Ramos Sañudo
Author-email: framos@yaco.es
License: LGPL v3
Keywords: django newsletter
Platform: UNKNOWN
